mm_btc_cli/__init__.py
mm_btc_cli/cli.py
mm_btc_cli/utils.py
mm_btc_cli/cmd/__init__.py
mm_btc_cli/cmd/address_cmd.py
mm_btc_cli/cmd/create_tx_cmd.py
mm_btc_cli/cmd/decode_tx_cmd.py
mm_btc_cli/cmd/mnemonic_cmd.py
mm_btc_cli/cmd/utxo_cmd.py
mm_btc_cli-0.1.0.dist-info/METADATA
mm_btc_cli-0.1.0.dist-info/WHEEL
mm_btc_cli-0.1.0.dist-info/entry_points.txt
mm_btc_cli-0.1.0.dist-info/RECORD
