Metadata-Version: 2.4
Name: mm-btc-cli
Version: 0.1.0
Requires-Python: >=3.12
Requires-Dist: mm-btc~=0.2.0
Requires-Dist: typer>=0.15.1
